Jong/__init__.py
Jong/convert.py
Jong/functions.py
Jong-1.0.8.dist-info/METADATA
Jong-1.0.8.dist-info/WHEEL
Jong-1.0.8.dist-info/top_level.txt
Jong-1.0.8.dist-info/RECORD
