Metadata-Version: 2.1
Name: Jong
Version: 1.0.8
Summary: https://github.com/Syniez/Syniez_module.git
Home-page: https://github.com/Syniez/Syniez_module.git
Author: Syniez
Author-email: js990204@naver.com
License: MIT
Platform: UNKNOWN
Classifier: Programming Language :: Python :: 3
Classifier: License :: OSI Approved :: MIT License
Classifier: Operating System :: OS Independent
Requires-Python: >=3.6
